StyleTransferTensorFlow/__init__.py
StyleTransferTensorFlow/convert.py
StyleTransferTensorFlow/extract.py
StyleTransferTensorFlow/make.py
StyleTransferTensorFlow/style.py
StyleTransferTensorFlow-0.1.3.dist-info/LICENSE.txt
StyleTransferTensorFlow-0.1.3.dist-info/METADATA
StyleTransferTensorFlow-0.1.3.dist-info/WHEEL
StyleTransferTensorFlow-0.1.3.dist-info/top_level.txt
StyleTransferTensorFlow-0.1.3.dist-info/RECORD
