Metadata-Version: 2.1
Name: StyleTransferTensorFlow
Version: 0.1.3
Summary: Package to apply style transfer on different frames of a video
Home-page: https://github.com/LordHarsh/Neural_Style_Transfer
Author: Hash Banka
Author-email: harshbanka321@gmail.com
License: MIT
Platform: UNKNOWN
Requires-Python: >=3.6
Requires-Dist: matplotlib
Requires-Dist: tensorflow
Requires-Dist: os-win
Requires-Dist: ffmpy
Requires-Dist: glob2
Requires-Dist: pytest-shutil
Requires-Dist: pytube
Requires-Dist: opencv-python
Requires-Dist: pillow
Requires-Dist: numpy
Requires-Dist: tensorflow-hub
